{
    "orders": [
      {
        "id": 1,
        "order_status": "Complete",
        "payment_status": "Paid",
        "shipping_status": "Delivered",
        "customer": "anik.barua@brainstation-23.com",
        "store": "Store name",
        "created": "03/13/2022",
        "order_total": "$40.00",
        "view": "View"
      },
      {
        "id": 2,
        "order_status": "Processing",
        "payment_status": "Paid",
        "shipping_status": "Delivered",
        "customer": "anik.barua@brainstation-23.com",
        "store": "Store name",
        "created": "03/13/2022",
        "order_total": "$40.00",
        "view": "View"
      },
      {
        "id": 3,
        "order_status": "Pending",
        "payment_status": "Paid",
        "shipping_status": "Delivered",
        "customer": "anik.barua@brainstation-23.com",
        "store": "Store name",
        "created": "03/13/2022",
        "order_total": "$40.00",
        "view": "View"
      },
      {
        "id": 4,
        "order_status": "Complete",
        "payment_status": "Paid",
        "shipping_status": "Delivered",
        "customer": "anik.barua@brainstation-23.com",
        "store": "Store name",
        "created": "03/13/2022",
        "order_total": "$40.00",
        "view": "View"
      },
      {
        "id": 5,
        "order_status": "Complete",
        "payment_status": "Paid",
        "shipping_status": "Delivered",
        "customer": "anik.barua@brainstation-23.com",
        "store": "Store name",
        "created": "03/13/2022",
        "order_total": "$40.00",
        "view": "View"
      },
      {
        "id": 6,
        "order_status": "Complete",
        "payment_status": "Paid",
        "shipping_status": "Delivered",
        "customer": "anik.barua@brainstation-23.com",
        "store": "Store name",
        "created": "03/13/2022",
        "order_total": "$40.00",
        "view": "View"
      },
      {
        "id": 7,
        "order_status": "Complete",
        "payment_status": "Paid",
        "shipping_status": "Delivered",
        "customer": "anik.barua@brainstation-23.com",
        "store": "Store name",
        "created": "03/13/2022",
        "order_total": "$40.00",
        "view": "View"
      },
      {
        "id": 8,
        "order_status": "Complete",
        "payment_status": "Paid",
        "shipping_status": "Delivered",
        "customer": "anik.barua@brainstation-23.com",
        "store": "Store name",
        "created": "03/13/2022",
        "order_total": "$40.00",
        "view": "View"
      },
      {
        "id": 9,
        "order_status": "Complete",
        "payment_status": "Paid",
        "shipping_status": "Delivered",
        "customer": "anik.barua@brainstation-23.com",
        "store": "Store name",
        "created": "03/13/2022",
        "order_total": "$40.00",
        "view": "View"
      },
      {
        "id": 10,
        "order_status": "Complete",
        "payment_status": "Paid",
        "shipping_status": "Delivered",
        "customer": "anik.barua@brainstation-23.com",
        "store": "Store name",
        "created": "03/13/2022",
        "order_total": "$40.00",
        "view": "View"
      },
      {
        "id": 11,
        "order_status": "Complete",
        "payment_status": "Paid",
        "shipping_status": "Delivered",
        "customer": "anik.barua@brainstation-23.com",
        "store": "Store name",
        "created": "03/13/2022",
        "order_total": "$40.00",
        "view": "View"
      },
      {
        "id": 12,
        "order_status": "Complete",
        "payment_status": "Paid",
        "shipping_status": "Delivered",
        "customer": "anik.barua@brainstation-23.com",
        "store": "Store name",
        "created": "03/13/2022",
        "order_total": "$40.00",
        "view": "View"
      } ,
      {
        "id": 13,
        "order_status": "Complete",
        "payment_status": "Paid",
        "shipping_status": "Delivered",
        "customer": "anik.barua@brainstation-23.com",
        "store": "Store name",
        "created": "03/13/2022",
        "order_total": "$40.00",
        "view": "View"
      } ,
      {
        "id": 14,
        "order_status": "Complete",
        "payment_status": "Paid",
        "shipping_status": "Delivered",
        "customer": "anik.barua@brainstation-23.com",
        "store": "Store name",
        "created": "03/13/2022",
        "order_total": "$40.00",
        "view": "View"
      } ,
      {
        "id": 15,
        "order_status": "Complete",
        "payment_status": "Paid",
        "shipping_status": "Delivered",
        "customer": "anik.barua@brainstation-23.com",
        "store": "Store name",
        "created": "03/13/2022",
        "order_total": "$40.00",
        "view": "View"
      } ,
      {
        "id": 16,
        "order_status": "Complete",
        "payment_status": "Paid",
        "shipping_status": "Delivered",
        "customer": "anik.barua@brainstation-23.com",
        "store": "Store name",
        "created": "03/13/2022",
        "order_total": "$40.00",
        "view": "View"
      } ,
      {
        "id": 17,
        "order_status": "Complete",
        "payment_status": "Paid",
        "shipping_status": "Delivered",
        "customer": "anik.barua@brainstation-23.com",
        "store": "Store name",
        "created": "03/13/2022",
        "order_total": "$40.00",
        "view": "View"
      } ,
      {
        "id": 18,
        "order_status": "Complete",
        "payment_status": "Paid",
        "shipping_status": "Delivered",
        "customer": "anik.barua@brainstation-23.com",
        "store": "Store name",
        "created": "03/13/2022",
        "order_total": "$40.00",
        "view": "View"
      } ,
      {
        "id": 19,
        "order_status": "Complete",
        "payment_status": "Paid",
        "shipping_status": "Delivered",
        "customer": "anik.barua@brainstation-23.com",
        "store": "Store name",
        "created": "03/13/2022",
        "order_total": "$40.00",
        "view": "View"
      } ,
      {
        "id": 20,
        "order_status": "Complete",
        "payment_status": "Paid",
        "shipping_status": "Delivered",
        "customer": "anik.barua@brainstation-23.com",
        "store": "Store name",
        "created": "03/13/2022",
        "order_total": "$40.00",
        "view": "View"
      } 
    ]
  }
  